{
  "id": 15285,
  "kuerzel": "U_SoPhoWi_SS06",
  "bezeichnung": "Sonnenenergie: Photovoltaik und Wind - Übergangsmodul SS 06",
  "kreditpunkte": 2,
  "lernziele": "Der Absolvent lernt die Grundlagen, das Potential und die technischen M&ouml;glichkeiten zur Nutzung der Sonnenenergie kennen",
  "semesterBewertung": "keine Note oder Wertung",
  "sprache": "de-CH",
  "zustand": "deaktiviert",
  "kurse": [
    {
      "id": 15288,
      "kuerzel": "uSoPhoWi_S6",
      "bezeichnung": "Sonnenenergie: Photovoltaik und Wind - Übergang SS 06",
      "planinhalt": "<p>1. Sonnenenergie: Grundlagen<br />- Die Sonne als Strahlungsquelle und Zeitreferenz (Strahlungsbilanz, Spektrum, Sonnenbahn und Sonnenzeit. <br />- Meteorologie und Simulation der Einstrahung. </p>\n<p>2. Photovoltaik<br />- Grundlagen der Halbleiterphysik <br />- Funktion und Kennwerte von Solarzellen <br />- Bauarten von Zellen und Modulen <br />- Photovoltaische Generatoren f&uuml;r Insel- und Netzparallelbetrieb <br />- Werkzeuge zur Bestimmung des Ertrages von Solaranlagen <br />- Wirtschaftlichkeit, Lebensdauer und Umweltvertr&auml;glichkeit von PV-Systemen. </p>\n<p>3. Windenergie<br />- Globale Windsysteme und ihre Entstehung <br />- Geschichte der Windenergienutzung <br />- Aerodynamische Grundlagen <br />- Bauarten und Komponenten von WEK <br />- Regelung und Netzanbindung von WEK <br />- Oekologie und Wirtschaftlichkeit </p>\n<p>.</p>",
      "kurselemente": [
        {
          "id": 15289,
          "art": "Vorlesung",
          "anzLektionen": 2,
          "maxTeilnehmer": 36,
          "harteGrenze": true
        }
      ],
      "uebersetzungen": [
        {
          "id": 3701,
          "bezeichnung": "Sonnenenergie: Photovoltaik und Wind - Übergang SS 06"
        },
        {
          "id": 3702,
          "bezeichnung": "Solar Energy: Photovoltaics and Wind - Transition SS 06"
        }
      ]
    }
  ],
  "zuordnungen": [
    {
      "id": 10007,
      "bezeichnung": "Maschinentechnik",
      "kuerzel": "M",
      "url": "allStudies/10007_M.json",
      "typ": "Standard",
      "istAbschlussArbeit": false,
      "istPflichtmodul": false,
      "semEmpfehlung": 0,
      "kategorien": [
        {
          "id": 10013,
          "kuerzel": "M-mt",
          "bezeichnung": "Maschinentechnik",
          "kreditpunkte": 2
        },
        {
          "id": 10089,
          "kuerzel": "M-mmn",
          "bezeichnung": "Maschinentechnik, Mathematik, Naturwissenschaften",
          "kreditpunkte": 2
        }
      ]
    },
    {
      "id": 10010,
      "bezeichnung": "Elektrotechnik",
      "kuerzel": "E",
      "url": "allStudies/10010_E.json",
      "typ": "Standard",
      "istAbschlussArbeit": false,
      "istPflichtmodul": false,
      "semEmpfehlung": 0,
      "kategorien": [
        {
          "id": 10000,
          "kuerzel": "E-et",
          "bezeichnung": "Technik",
          "kreditpunkte": 2
        }
      ]
    },
    {
      "id": 10013,
      "bezeichnung": "Maschinentechnik",
      "kuerzel": "M",
      "url": "allStudies/10013_M.json",
      "typ": "Standard",
      "istAbschlussArbeit": false,
      "istPflichtmodul": false,
      "semEmpfehlung": 0,
      "kategorien": [
        {
          "id": 10066,
          "kuerzel": "K_U2M",
          "bezeichnung": "Übergangsmodule Maschinentechnik 2 (Jahrgang 2001)",
          "kreditpunkte": 2
        }
      ]
    }
  ],
  "dozenten": [
    {
      "id": 147,
      "name": "Prechtl",
      "vorname": "Heiner"
    }
  ],
  "orte": [
    {
      "id": 4,
      "kuerzel": "RJ",
      "bezeichnung": "Rapperswil-Jona",
      "ort": "8640 Rapperswil"
    }
  ],
  "pruefung": [
    {
      "id": 15285,
      "art": "Note von 1 - 6",
      "pruefungMue": false,
      "pruefungSchr": true,
      "dauerPrfSchr": 75,
      "zulassung": false,
      "prfAbmeldbar": true
    }
  ],
  "uebersetzungen": [
    {
      "id": 3701,
      "sprache": "de-CH",
      "bezeichnung": "Sonnenenergie: Photovoltaik und Wind - Übergangsmodul SS 06"
    },
    {
      "id": 3702,
      "sprache": "en-US",
      "bezeichnung": "Solar Energy: Photovoltaics and Wind - Bridging Module SS 06"
    }
  ],
  "skriptAblageLink": "https://moodle.ost.ch",
  "durchfuehrungen": {
    "beginJahr": 2006,
    "beginSemester": "SS",
    "endJahr": 2006,
    "endSemester": "SS"
  }
}