{
  "id": 18614,
  "kuerzel": "M_FZ1",
  "bezeichnung": "Freihandzeichnen",
  "kreditpunkte": 2,
  "lernziele": "<ul>\n    <li>Vermittlung differenzierter Darstellungsmethoden f&uuml;r spezielle fachliche Entwurfs- und Planungsaufgaben</li>\n</ul>",
  "semesterBewertung": "Note von 1 - 6",
  "sprache": "de-CH",
  "zustand": "aktiviert",
  "kurse": [
    {
      "id": 18623,
      "kuerzel": "FZ1",
      "bezeichnung": "Freihandzeichnen 1",
      "lernziele": "<ul>\n    <li>Sicherheit im Umgang mit Freihandzeichnen und Skizzieren</li>\n    <li>Vertiefung der zeichnerischen und bildnerischen F&auml;higkeiten</li>\n    <li>Entwicklung des Raumvorstellungsverm&ouml;gens</li>\n</ul>",
      "planinhalt": "<p>Wahrnehmung und Darstellung von Raum, Plastizit&auml;t, K&ouml;rperlichkeit, Licht und Materialien; <br />Landschafts-, Vegetations- und Architekturzeichnung;<br />begleitende Theorie </p>",
      "kurselemente": [
        {
          "id": 18907,
          "art": "Uebung",
          "anzLektionen": 2,
          "maxTeilnehmer": 18,
          "harteGrenze": true
        }
      ],
      "uebersetzungen": [
        {
          "id": 3701,
          "bezeichnung": "Freihandzeichnen 1"
        },
        {
          "id": 3702,
          "bezeichnung": "Drawing 1"
        }
      ]
    }
  ],
  "zuordnungen": [
    {
      "id": 10002,
      "bezeichnung": "Landschaftsarchitektur",
      "kuerzel": "L",
      "url": "allStudies/10002_L.json",
      "typ": "Standard",
      "istAbschlussArbeit": false,
      "istPflichtmodul": false,
      "semEmpfehlung": 1,
      "kategorien": [
        {
          "id": 10018,
          "kuerzel": "L-g",
          "bezeichnung": "Grundlagenmodule Landschaftsarchitektur",
          "kreditpunkte": 2
        }
      ]
    },
    {
      "id": 10008,
      "bezeichnung": "Landschaftsarchitektur",
      "kuerzel": "L",
      "url": "allStudies/10008_L.json",
      "typ": "Standard",
      "istAbschlussArbeit": false,
      "istPflichtmodul": false,
      "semEmpfehlung": 1,
      "kategorien": [
        {
          "id": 10018,
          "kuerzel": "L-g",
          "bezeichnung": "Grundlagenmodule Landschaftsarchitektur",
          "kreditpunkte": 2
        }
      ]
    },
    {
      "id": 10061,
      "bezeichnung": "Landschaftsarchitektur",
      "kuerzel": "L",
      "url": "allStudies/10061_L.json",
      "typ": "Standard",
      "istAbschlussArbeit": false,
      "istPflichtmodul": false,
      "semEmpfehlung": 1,
      "kategorien": [
        {
          "id": 10019,
          "kuerzel": "L-p",
          "bezeichnung": "Profilmodule Landschaftsarchitektur",
          "kreditpunkte": 2
        }
      ]
    },
    {
      "id": 10112,
      "bezeichnung": "Landschaftsarchitektur",
      "kuerzel": "L",
      "url": "allStudies/10112_L.json",
      "typ": "Standard",
      "istAbschlussArbeit": false,
      "istPflichtmodul": false,
      "semEmpfehlung": 1,
      "kategorien": [
        {
          "id": 10019,
          "kuerzel": "L-p",
          "bezeichnung": "Profilmodule Landschaftsarchitektur",
          "kreditpunkte": 2
        }
      ]
    },
    {
      "id": 10152,
      "bezeichnung": "Landschaftsarchitektur",
      "kuerzel": "L",
      "url": "allStudies/10152_L.json",
      "typ": "Standard",
      "istAbschlussArbeit": false,
      "istPflichtmodul": false,
      "semEmpfehlung": 1,
      "kategorien": [
        {
          "id": 10019,
          "kuerzel": "L-p",
          "bezeichnung": "Profilmodule Landschaftsarchitektur",
          "kreditpunkte": 2
        }
      ]
    },
    {
      "id": 10199,
      "bezeichnung": "Landschaftsarchitektur",
      "kuerzel": "L",
      "url": "allStudies/10199_L.json",
      "typ": "Standard",
      "istAbschlussArbeit": false,
      "istPflichtmodul": false,
      "semEmpfehlung": 1,
      "kategorien": [
        {
          "id": 10019,
          "kuerzel": "L-p",
          "bezeichnung": "Profilmodule Landschaftsarchitektur",
          "kreditpunkte": 2
        }
      ]
    },
    {
      "id": 10264,
      "bezeichnung": "Landschaftsarchitektur",
      "kuerzel": "L",
      "url": "allStudies/10264_L.json",
      "typ": "Standard",
      "istAbschlussArbeit": false,
      "istPflichtmodul": false,
      "semEmpfehlung": 1,
      "kategorien": [
        {
          "id": 10019,
          "kuerzel": "L-p",
          "bezeichnung": "Profilmodule Landschaftsarchitektur",
          "kreditpunkte": 2
        }
      ]
    }
  ],
  "dozenten": [
    {
      "id": 1233,
      "name": "Cejka",
      "vorname": "Andrea"
    }
  ],
  "orte": [
    {
      "id": 4,
      "kuerzel": "RJ",
      "bezeichnung": "Rapperswil-Jona",
      "ort": "8640 Rapperswil"
    }
  ],
  "uebersetzungen": [
    {
      "id": 3701,
      "sprache": "de-CH",
      "bezeichnung": "Freihandzeichnen"
    },
    {
      "id": 3702,
      "sprache": "en-US",
      "bezeichnung": "Drawing"
    }
  ],
  "skriptAblageLink": "https://moodle.ost.ch",
  "durchfuehrungen": {
    "count": 1,
    "beginJahr": 2010,
    "beginSemester": "FS",
    "endJahr": 2026,
    "endSemester": "HS"
  }
}