{
  "id": 31473,
  "kuerzel": "M_Ewu4",
  "bezeichnung": "Entwurf 4 (2018)",
  "kreditpunkte": 6,
  "lernziele": "<ul><li>F&auml;higkeit zur effizienten und selbst&auml;ndigen Bearbeitung eines eigenst&auml;ndigen landschaftsarchitektonischen Entwurfs</li><li>F&auml;higkeit, f&uuml;r einen spezifischen OIrt und eine spezifische Aufgabe ein konsistentes Konzept zu entwickeln und gestalterisch umzusetzen</li><li>Entwickeln einer ganzheitlichen Entwurfshaltung im Hinblick auf &Auml;sthetik, Funktionalit&auml;t, &Ouml;kologie und Angemessenheit der L&ouml;sung</li><li>Gestalten einzelner landschaftsarchitektonischer Elemente (Material- und Pflanzenverwendung, Formgebung)</li></ul><p>&nbsp;</p>",
  "semesterBewertung": "keine Note oder Wertung",
  "sprache": "de-CH",
  "zustand": "deaktiviert",
  "kurse": [
    {
      "id": 31474,
      "kuerzel": "WoD",
      "bezeichnung": "Wohnen, Dienstleistungen",
      "planinhalt": "<p>Entwurfsprojekt mit typischen r&auml;umlichen, funktionalen und gestalterischen Problemstellungen bis Stufe Vorprojekt inklusive Leitdetails.<br />Entwurfsschwerpunkt: Wohnumfeld. Gegenstand ist in der Regel die Umgebungsgestaltung einer Wohnsiedlung mit Fragen zur nachhaltigen Entwicklung, zur ganzheitlichen Gestaltung unter besonderer Ber&uuml;cksichtigung des Nutzerverhaltens. Gestalterische Fragen wie Ortsbezug, Raumbildung, Formgebung, Materialisierung und Bepflanzung stehen im Zentrum. Weitere Themen sind der gestalterisch-konstruktive Umgang mit baulichen Elementen wie Treppen, Mauern, Becken und Pergolen sowie die langfristige Entwicklung, Pflege und Unterhalt.<br />Plandarstellung und Modell: Analysepl&auml;ne, Konzeptdiagramme, Vorprojektpl&auml;ne mit Schnitten und perspektivischen Visualisierungen, teilweise Leitdetail- und Pflanzpl&auml;ne, Arbeitsmodell</p>",
      "kurselemente": [
        {
          "id": 31475,
          "art": "Projekt",
          "anzLektionen": 2,
          "maxTeilnehmer": 72,
          "harteGrenze": true
        },
        {
          "id": 31476,
          "art": "Uebung",
          "anzLektionen": 4,
          "maxTeilnehmer": 18,
          "harteGrenze": true
        }
      ],
      "uebersetzungen": [
        {
          "id": 3701,
          "bezeichnung": "Wohnen, Dienstleistungen"
        },
        {
          "id": 3702,
          "bezeichnung": "Residential Areas, Service Industries"
        }
      ]
    }
  ],
  "zuordnungen": [
    {
      "id": 10061,
      "bezeichnung": "Landschaftsarchitektur",
      "kuerzel": "L",
      "url": "allStudies/10061_L.json",
      "typ": "Standard",
      "istAbschlussArbeit": false,
      "istPflichtmodul": false,
      "semEmpfehlung": 4,
      "kategorien": [
        {
          "id": 10019,
          "kuerzel": "L-p",
          "bezeichnung": "Profilmodule Landschaftsarchitektur",
          "kreditpunkte": 6
        }
      ]
    },
    {
      "id": 10112,
      "bezeichnung": "Landschaftsarchitektur",
      "kuerzel": "L",
      "url": "allStudies/10112_L.json",
      "typ": "Standard",
      "istAbschlussArbeit": false,
      "istPflichtmodul": false,
      "semEmpfehlung": 4,
      "kategorien": [
        {
          "id": 10019,
          "kuerzel": "L-p",
          "bezeichnung": "Profilmodule Landschaftsarchitektur",
          "kreditpunkte": 6
        }
      ]
    },
    {
      "id": 10152,
      "bezeichnung": "Landschaftsarchitektur",
      "kuerzel": "L",
      "url": "allStudies/10152_L.json",
      "typ": "Standard",
      "istAbschlussArbeit": false,
      "istPflichtmodul": false,
      "semEmpfehlung": 4,
      "kategorien": [
        {
          "id": 10019,
          "kuerzel": "L-p",
          "bezeichnung": "Profilmodule Landschaftsarchitektur",
          "kreditpunkte": 6
        }
      ]
    },
    {
      "id": 10077,
      "bezeichnung": "Planung und Entwurf urbaner Freiräume",
      "kuerzel": "PlaEntw",
      "url": "allStudies/10077_PlaEntw.json",
      "typ": "Standard",
      "istAbschlussArbeit": false,
      "istPflichtmodul": false,
      "semEmpfehlung": 0
    },
    {
      "id": 10157,
      "bezeichnung": "Planung und Entwurf",
      "kuerzel": "L_PlaEw",
      "url": "allStudies/10157_L_PlaEw.json",
      "typ": "Standard",
      "istAbschlussArbeit": false,
      "istPflichtmodul": false,
      "semEmpfehlung": 0
    },
    {
      "id": 10071,
      "bezeichnung": "Planung und Entwurf urbaner Freiräume",
      "kuerzel": "PlanEntw",
      "url": "allStudies/10071_PlanEntw.json",
      "typ": "Standard",
      "istAbschlussArbeit": false,
      "istPflichtmodul": false,
      "semEmpfehlung": 0
    },
    {
      "id": 10113,
      "bezeichnung": "Landschaftsbau- und Management",
      "kuerzel": "LaBau",
      "url": "allStudies/10113_LaBau.json",
      "typ": "Standard",
      "istAbschlussArbeit": false,
      "istPflichtmodul": false,
      "semEmpfehlung": 0
    },
    {
      "id": 10073,
      "bezeichnung": "Landschaftsbau- und Management",
      "kuerzel": "LaBau",
      "url": "allStudies/10073_LaBau.json",
      "typ": "Standard",
      "istAbschlussArbeit": false,
      "istPflichtmodul": false,
      "semEmpfehlung": 0
    },
    {
      "id": 10115,
      "bezeichnung": "Planung und Entwurf urbaner Freiräume",
      "kuerzel": "PlaEntw",
      "url": "allStudies/10115_PlaEntw.json",
      "typ": "Standard",
      "istAbschlussArbeit": false,
      "istPflichtmodul": false,
      "semEmpfehlung": 0
    },
    {
      "id": 10075,
      "bezeichnung": "Landschaftsbau- und Management",
      "kuerzel": "LaBau",
      "url": "allStudies/10075_LaBau.json",
      "typ": "Standard",
      "istAbschlussArbeit": false,
      "istPflichtmodul": false,
      "semEmpfehlung": 0
    },
    {
      "id": 10158,
      "bezeichnung": "Landschaftsbau und Management",
      "kuerzel": "L_LBMgmt",
      "url": "allStudies/10158_L_LBMgmt.json",
      "typ": "Standard",
      "istAbschlussArbeit": false,
      "istPflichtmodul": false,
      "semEmpfehlung": 0
    }
  ],
  "dozenten": [
    {
      "id": 531138,
      "name": "Gadient",
      "vorname": "Hansjörg"
    }
  ],
  "empfehlungen": [
    {
      "id": 31448,
      "kuerzel": "M_Ewu2",
      "bezeichnung": "Entwurf 2 (2018)",
      "url": "allModules/31448_M_Ewu2.json"
    },
    {
      "id": 31464,
      "kuerzel": "M_Ewu3",
      "bezeichnung": "Entwurf 3 (2018)",
      "url": "allModules/31464_M_Ewu3.json"
    },
    {
      "id": 36083,
      "kuerzel": "M_Entwu1",
      "bezeichnung": "Entwurf 1",
      "url": "allModules/36083_M_Entwu1.json"
    }
  ],
  "orte": [
    {
      "id": 4,
      "kuerzel": "RJ",
      "bezeichnung": "Rapperswil-Jona",
      "ort": "8640 Rapperswil"
    }
  ],
  "pruefung": [
    {
      "id": 31473,
      "art": "Note von 1 - 6",
      "pruefungMue": true,
      "dauerPrfMue": 20,
      "pruefungSchr": false,
      "zulassung": true,
      "zulassungsBedingung": "<ul> <li>Fristgerechte Abgabe der Arbeit, </li> <li>Teilnahme an den Zwischenkritiken, </li> <li>Stand&nbsp;von Arbeitsheft, Projektpl&auml;nen und Arbeitsmodell zum Zeitpunkt der Schlusskritik gen&uuml;gend. </li> </ul> <p>&nbsp;</p>",
      "prfAbmeldbar": true
    }
  ],
  "uebersetzungen": [
    {
      "id": 3701,
      "sprache": "de-CH",
      "bezeichnung": "Entwurf 4"
    },
    {
      "id": 3702,
      "sprache": "en-US",
      "bezeichnung": "Landscape Design 4"
    }
  ],
  "skriptAblageLink": "https://moodle.ost.ch",
  "durchfuehrungen": {
    "beginJahr": 2019,
    "beginSemester": "FS",
    "endJahr": 2019,
    "endSemester": "FS"
  },
  "vorgaenger": {
    "id": 24264,
    "kuerzel": "M_Entwu3",
    "bezeichnung": "Entwurf 3",
    "url": "allModules/24264_M_Entwu3.json"
  },
  "nachfolger": {
    "id": 31473,
    "kuerzel": "M_Ewu4",
    "bezeichnung": "Entwurf 4 (2018)",
    "url": "allModules/31473_M_Ewu4.json"
  }
}