{
  "id": 24747,
  "kuerzel": "M_BAWVOR",
  "bezeichnung": "Bachelor-Arbeit - Vorbereitung",
  "kreditpunkte": 4,
  "lernziele": "<p>Das Modul dient prim&auml;r dazu, die Studierenden auf eine selbst&auml;ndige, wissenschaftliche Arbeit vorzubereiten. Das dazu notwendige Fachwissen wird den Studierenden in einem Theorieblock vermittelt, der in Form eines E-Learning Kurses angeboten wird.<br />Die Studierenden lernen, eine gestellte Aufgabe selbst&auml;ndig und effizient zu bearbeiten, Daten zu recherchieren, Schlussfolgerungen zu ziehen und die Ergebnisse in einem kurzen Bericht zusammenzufassen und zu pr&auml;sentieren.<br />Die Recherchearbeit ist eine in sich geschlossene Arbeit mit Bewertung, kann aber dazu dienen, dass sich die Studierenden in das Themenfeld der sp&auml;teren Bachelorarbeit einarbeiten.<br />Zu erwerbende F&auml;higkeiten: Grunds&auml;tze wissenschaftlichen Arbeitens verstehen und anwenden, Analyse und Bearbeitungsplanung einer gestellten Aufgabe; Beschaffung n&ouml;tiger Informationen; eigene Schlussfolgerungen ziehen und begr&uuml;nden, adressatengerechte Dokumentation und Pr&auml;sentation.</p>",
  "vorausgKenntnisse": "<p>Englisch Niveau B2</p>",
  "semesterBewertung": "Note von 1 - 6",
  "sprache": "de-CH",
  "zustand": "deaktiviert",
  "kurse": [
    {
      "id": 24748,
      "kuerzel": "RA",
      "bezeichnung": "Recherchearbeit",
      "lernziele": "<p>Umsetzen und Ein&uuml;ben der erworbenen Fachkenntnisse aus dem Studium und dem E-Learning Kurs &bdquo;Academic Research&ldquo; anhand einer konkreten Aufgabenstellung.</p>",
      "planinhalt": "<p>entsprechend der individuellen Aufgabenstellung.</p>",
      "kurselemente": [
        {
          "id": 24751,
          "art": "Studienarbeit",
          "anzLektionen": 3.5,
          "maxTeilnehmer": 100,
          "harteGrenze": true
        }
      ],
      "uebersetzungen": [
        {
          "id": 3701,
          "bezeichnung": "Recherchearbeit"
        },
        {
          "id": 3702,
          "bezeichnung": "Research"
        }
      ]
    },
    {
      "id": 28682,
      "kuerzel": "eAR",
      "bezeichnung": "Academic Research - E-Learning",
      "lernziele": "<p>Grunds&auml;tze wissenschaftlichen Arbeitens verstehen und anwenden.</p>",
      "planinhalt": "<p>Die Studierenden werden mit multimedialen Kursunterlagen in folgende Themen eingef&uuml;hrt:<br />-&nbsp;The rationale of academic research<br />-&nbsp;Posing the question<br />- Organizing your project<br />-&nbsp;Information literacy<br />- Literature search<br />- Managing your references<br />- Creating the outlines<br />- Citing and referencing<br />-&nbsp;Phrasing and visualizing<br />- Revising</p><p>E-Learning Kurs. Die Studierenden bearbeiten in Eigenverantwortung und&nbsp;zeitlich flexibel die &Uuml;bungen in Englisch</p>",
      "kurselemente": [
        {
          "id": 28683,
          "art": "Selbststudium",
          "anzLektionen": 0.5,
          "maxTeilnehmer": 100,
          "harteGrenze": true
        }
      ],
      "uebersetzungen": [
        {
          "id": 3701,
          "bezeichnung": "Academic Research"
        },
        {
          "id": 3702,
          "bezeichnung": "Academic Research"
        }
      ]
    }
  ],
  "zuordnungen": [
    {
      "id": 10104,
      "bezeichnung": "Wirtschaftsingenieurwesen",
      "kuerzel": "WING",
      "url": "allStudies/10104_WING.json",
      "typ": "Standard",
      "istAbschlussArbeit": false,
      "istPflichtmodul": true,
      "semEmpfehlung": 5,
      "kategorien": [
        {
          "id": 10121,
          "kuerzel": "W-KS",
          "bezeichnung": "Kontextstudium",
          "kreditpunkte": 4
        },
        {
          "id": 10130,
          "kuerzel": "W-KSpl",
          "bezeichnung": "Kontextstudium und ergänzende Fachmodule",
          "kreditpunkte": 4
        }
      ]
    },
    {
      "id": 10129,
      "bezeichnung": "Wirtschaftsingenieurwesen",
      "kuerzel": "WING",
      "url": "allStudies/10129_WING.json",
      "typ": "Standard",
      "istAbschlussArbeit": false,
      "istPflichtmodul": true,
      "semEmpfehlung": 5,
      "kategorien": [
        {
          "id": 10121,
          "kuerzel": "W-KS",
          "bezeichnung": "Kontextstudium",
          "kreditpunkte": 4
        },
        {
          "id": 10130,
          "kuerzel": "W-KSpl",
          "bezeichnung": "Kontextstudium und ergänzende Fachmodule",
          "kreditpunkte": 4
        }
      ]
    },
    {
      "id": 10130,
      "bezeichnung": "Wirtschaftsingenieurwesen",
      "kuerzel": "WING",
      "url": "allStudies/10130_WING.json",
      "typ": "Standard",
      "istAbschlussArbeit": false,
      "istPflichtmodul": true,
      "semEmpfehlung": 5,
      "kategorien": [
        {
          "id": 10121,
          "kuerzel": "W-KS",
          "bezeichnung": "Kontextstudium",
          "kreditpunkte": 4
        },
        {
          "id": 10130,
          "kuerzel": "W-KSpl",
          "bezeichnung": "Kontextstudium und ergänzende Fachmodule",
          "kreditpunkte": 4
        }
      ]
    },
    {
      "id": 10151,
      "bezeichnung": "Wirtschaftsingenieurwesen",
      "kuerzel": "WING",
      "url": "allStudies/10151_WING.json",
      "typ": "Standard",
      "istAbschlussArbeit": false,
      "istPflichtmodul": true,
      "semEmpfehlung": 5,
      "kategorien": [
        {
          "id": 10121,
          "kuerzel": "W-KS",
          "bezeichnung": "Kontextstudium",
          "kreditpunkte": 4
        }
      ]
    },
    {
      "id": 10169,
      "bezeichnung": "Wirtschaftsingenieurwesen",
      "kuerzel": "WING",
      "url": "allStudies/10169_WING.json",
      "typ": "Standard",
      "istAbschlussArbeit": false,
      "istPflichtmodul": true,
      "semEmpfehlung": 5,
      "kategorien": [
        {
          "id": 10121,
          "kuerzel": "W-KS",
          "bezeichnung": "Kontextstudium",
          "kreditpunkte": 4
        }
      ]
    }
  ],
  "dozenten": [
    {
      "id": 540086,
      "name": "Keller",
      "vorname": "Daniel F."
    }
  ],
  "orte": [
    {
      "id": 4,
      "kuerzel": "RJ",
      "bezeichnung": "Rapperswil-Jona",
      "ort": "8640 Rapperswil"
    }
  ],
  "uebersetzungen": [
    {
      "id": 3701,
      "sprache": "de-CH",
      "bezeichnung": "Bachelor-Arbeit - Vorbereitung"
    },
    {
      "id": 3702,
      "sprache": "en-US",
      "bezeichnung": "Bachelor Thesis - Preliminaries"
    }
  ],
  "skriptAblageLink": "https://moodle.ost.ch",
  "durchfuehrungen": {
    "beginJahr": 2016,
    "beginSemester": "HS",
    "endJahr": 2018,
    "endSemester": "FS"
  },
  "nachfolger": {
    "id": 24747,
    "kuerzel": "M_BAWVOR",
    "bezeichnung": "Bachelor-Arbeit - Vorbereitung",
    "url": "allModules/24747_M_BAWVOR.json"
  }
}