{
  "id": 29340,
  "kuerzel": "M_OOSchutz",
  "bezeichnung": "Ortsbild- und Objektschutz",
  "kreditpunkte": 2,
  "lernziele": "<p>Auseinandersetzung mit praktischen Problem- und Aufgabenstellungen im Bereich des Ortsbild- und Objektschutzes</p>",
  "semesterBewertung": "keine Note oder Wertung",
  "sprache": "de-CH",
  "zustand": "aktiviert",
  "kurse": [
    {
      "id": 29341,
      "kuerzel": "OOSchutz",
      "bezeichnung": "Ortsbild- und Objektschutz",
      "lernziele": "<p>&#8226; Kennenlernen von Begriffen <br />&#8226; Schnellkurs Architektur- und Stilgeschichte <br />&#8226; Kennenlernen von Orten, Ortsstrukturen, Ortsatmosph&#228;ren <br />&#8226; Vertraut sein mit Inventaren, Schutzkriterien, Rechtsfragen <br />&#8226; Vermittlung von theoretischen und praktischen Kompetenzen </p>",
      "planinhalt": "<p>&bull; Architektur, Technik und Materialisierung <br />&bull; Baustile und ihr kultureller Kontext <br />&bull; Baustellen, Kulturdenkm&auml;ler und Ortsbilder <br />&bull; Geschichte von Denkmalpflege und Ortsbildschutz <br />&bull; Inventare und Schutzkriterien <br />&bull; Rechtsgrundlagen, Verfahren, Mitwirkung <br />&bull; Rechtsfragen und Rechtsf&auml;lle <br />&bull; Grundhaltungen, Verschiebungen <br />&bull; Neugestaltung, Umnutzungen, Gewinne, Verluste <br />&bull; &Uuml;bung, Exkursion</p>",
      "kurselemente": [
        {
          "id": 29342,
          "art": "Vorlesung",
          "anzLektionen": 2,
          "maxTeilnehmer": 72,
          "harteGrenze": true
        }
      ],
      "uebersetzungen": [
        {
          "id": 3701,
          "bezeichnung": "Ortsbild- und Objektschutz"
        },
        {
          "id": 3702,
          "bezeichnung": "Heritage Protection"
        }
      ]
    }
  ],
  "zuordnungen": [
    {
      "id": 10041,
      "bezeichnung": "Raumplanung",
      "kuerzel": "R",
      "url": "allStudies/10041_R.json",
      "typ": "Standard",
      "istAbschlussArbeit": false,
      "istPflichtmodul": false,
      "semEmpfehlung": 5,
      "kategorien": [
        {
          "id": 10036,
          "kuerzel": "R-gwr",
          "bezeichnung": "Gesellschaft, Wirtschaft und Recht",
          "kreditpunkte": 2
        }
      ]
    },
    {
      "id": 10123,
      "bezeichnung": "Raumplanung",
      "kuerzel": "R",
      "url": "allStudies/10123_R.json",
      "typ": "Standard",
      "istAbschlussArbeit": false,
      "istPflichtmodul": false,
      "semEmpfehlung": 5,
      "kategorien": [
        {
          "id": 10036,
          "kuerzel": "R-gwr",
          "bezeichnung": "Gesellschaft, Wirtschaft und Recht",
          "kreditpunkte": 2
        }
      ]
    },
    {
      "id": 10142,
      "bezeichnung": "Stadt-, Verkehrs- und Raumplanung ",
      "kuerzel": "SVR",
      "url": "allStudies/10142_SVR.json",
      "typ": "Standard",
      "istAbschlussArbeit": false,
      "istPflichtmodul": false,
      "semEmpfehlung": 5,
      "kategorien": [
        {
          "id": 10036,
          "kuerzel": "R-gwr",
          "bezeichnung": "Gesellschaft, Wirtschaft und Recht",
          "kreditpunkte": 2
        }
      ]
    },
    {
      "id": 10201,
      "bezeichnung": "Stadt-, Verkehrs- und Raumplanung",
      "kuerzel": "SVR",
      "url": "allStudies/10201_SVR.json",
      "typ": "Standard",
      "istAbschlussArbeit": false,
      "istPflichtmodul": false,
      "semEmpfehlung": 5,
      "kategorien": [
        {
          "id": 10036,
          "kuerzel": "R-gwr",
          "bezeichnung": "Gesellschaft, Wirtschaft und Recht",
          "kreditpunkte": 2
        }
      ]
    },
    {
      "id": 10268,
      "bezeichnung": "Stadt-, Verkehrs- und Raumplanung",
      "kuerzel": "SVR",
      "url": "allStudies/10268_SVR.json",
      "typ": "Standard",
      "istAbschlussArbeit": false,
      "istPflichtmodul": false,
      "semEmpfehlung": 5,
      "kategorien": [
        {
          "id": 10036,
          "kuerzel": "R-gwr",
          "bezeichnung": "Gesellschaft, Wirtschaft und Recht",
          "kreditpunkte": 2
        }
      ]
    }
  ],
  "dozenten": [
    {
      "id": 5023059,
      "name": "Herdt",
      "vorname": "Tanja"
    }
  ],
  "empfehlungen": [
    {
      "id": 29163,
      "kuerzel": "M_KgsArch",
      "bezeichnung": "Kulturgeschichte: Architektur- und Stadtbaugeschichte",
      "url": "allModules/29163_M_KgsArch.json"
    }
  ],
  "orte": [
    {
      "id": 4,
      "kuerzel": "RJ",
      "bezeichnung": "Rapperswil-Jona",
      "ort": "8640 Rapperswil"
    }
  ],
  "pruefung": [
    {
      "id": 29340,
      "art": "Note von 1 - 6",
      "pruefungMue": false,
      "pruefungSchr": true,
      "dauerPrfSchr": 60,
      "zulassung": true,
      "zulassungsBedingung": "Abgabe Uebung/Teilnahme Exkursion",
      "prfAbmeldbar": true
    }
  ],
  "uebersetzungen": [
    {
      "id": 3701,
      "sprache": "de-CH",
      "bezeichnung": "Ortsbild- und Objektschutz"
    },
    {
      "id": 3702,
      "sprache": "en-US",
      "bezeichnung": "Heritage Protection"
    }
  ],
  "skriptAblageLink": "https://moodle.ost.ch",
  "durchfuehrungen": {
    "count": 2,
    "beginJahr": 2019,
    "beginSemester": "HS",
    "endJahr": 2026,
    "endSemester": "HS"
  },
  "vorgaenger": {
    "id": 21321,
    "kuerzel": "M_OOSchutz",
    "bezeichnung": "Ortsbild- und Objektschutz",
    "url": "allModules/21321_M_OOSchutz.json"
  }
}