{
  "id": 29892,
  "kuerzel": "U_Plieg2",
  "bezeichnung": "Planungs- und Liegenschaftenmanagement 2 (Übergang)",
  "kreditpunkte": 2,
  "lernziele": "<p>Kennenlernen der Stadterneuerungsmechanismen und Erlernen der Handlungs- und Entwurfs-Strategien in de rSiedlungsentwicklung</p>",
  "semesterBewertung": "keine Note oder Wertung",
  "sprache": "de-CH",
  "zustand": "deaktiviert",
  "kurse": [
    {
      "id": 29896,
      "kuerzel": "uPuLMan2",
      "bezeichnung": "Planungs- und Liegenschaftenmanagement 2",
      "lernziele": "<p>&#220;berblick &#252;ber die Baufinanzierungund das Mietwesen.<br />Kennenlernen der Methoden und Inhalte von Liegenschaftssch&#228;tzung und deren Bewirtschaftung.</p>",
      "planinhalt": "<p>Baufinanzierung: Mietzins, Hypothekarzins, Teuerung, Wirtschaftlichkeit, Subventionierung<br />Bau- und Immobilienmarkt: Immobilien-Monitoring und Standortqualit&auml;t<br />Liegenschaftensch&auml;tzung: Methoden, Bewertungssysteme und Faktoren, Finanzierungsmodelle <br />Liegenschaftsbewirtschaftung: Grundlagen der Sanierung und der Umnutzung. <br />Besprechung ausgew&auml;hlter Probleme bei Sch&auml;tzungen und Bewirtschaftungen <br />Facility-Management<br /></p>",
      "kurselemente": [
        {
          "id": 29897,
          "art": "Vorlesung",
          "anzLektionen": 2,
          "maxTeilnehmer": 72,
          "harteGrenze": true
        }
      ],
      "uebersetzungen": [
        {
          "id": 3701,
          "bezeichnung": "Planungs- und Liegenschaftenmanagement 2"
        },
        {
          "id": 3702,
          "bezeichnung": "Planning- and Real Estate Management 2"
        }
      ]
    }
  ],
  "zuordnungen": [
    {
      "id": 10041,
      "bezeichnung": "Raumplanung",
      "kuerzel": "R",
      "url": "allStudies/10041_R.json",
      "typ": "Standard",
      "istAbschlussArbeit": false,
      "istPflichtmodul": false,
      "semEmpfehlung": 4,
      "kategorien": [
        {
          "id": 10025,
          "kuerzel": "R-s",
          "bezeichnung": "Städtebau",
          "kreditpunkte": 2
        }
      ]
    },
    {
      "id": 10123,
      "bezeichnung": "Raumplanung",
      "kuerzel": "R",
      "url": "allStudies/10123_R.json",
      "typ": "Standard",
      "istAbschlussArbeit": false,
      "istPflichtmodul": false,
      "semEmpfehlung": 4,
      "kategorien": [
        {
          "id": 10025,
          "kuerzel": "R-s",
          "bezeichnung": "Städtebau",
          "kreditpunkte": 2
        }
      ]
    }
  ],
  "dozenten": [
    {
      "id": 541730,
      "name": "Gasser",
      "vorname": "Markus"
    }
  ],
  "empfehlungen": [
    {
      "id": 22365,
      "kuerzel": "M_St2",
      "bezeichnung": "Städtebau 2",
      "url": "allModules/22365_M_St2.json"
    }
  ],
  "orte": [
    {
      "id": 4,
      "kuerzel": "RJ",
      "bezeichnung": "Rapperswil-Jona",
      "ort": "8640 Rapperswil"
    }
  ],
  "pruefung": [
    {
      "id": 29892,
      "art": "Note von 1 - 6",
      "pruefungMue": false,
      "pruefungSchr": true,
      "dauerPrfSchr": 60,
      "zulassung": false,
      "prfAbmeldbar": true
    }
  ],
  "uebersetzungen": [
    {
      "id": 3701,
      "sprache": "de-CH",
      "bezeichnung": "Planungs- und Liegenschaftenmanagement 2"
    },
    {
      "id": 3702,
      "sprache": "en-US",
      "bezeichnung": "Planning- and Real Estate Management 2"
    }
  ],
  "skriptAblageLink": "https://moodle.ost.ch",
  "durchfuehrungen": {
    "beginJahr": 2018,
    "beginSemester": "FS",
    "endJahr": 2018,
    "endSemester": "FS"
  }
}